LICENSE
MANIFEST.in
README.rst
setup.py
django_gis_brasil.egg-info/PKG-INFO
django_gis_brasil.egg-info/SOURCES.txt
django_gis_brasil.egg-info/dependency_links.txt
django_gis_brasil.egg-info/not-zip-safe
django_gis_brasil.egg-info/requires.txt
django_gis_brasil.egg-info/top_level.txt
gisbrasil/__init__.py
gisbrasil/admin.py
gisbrasil/models.py
gisbrasil/tests.py
gisbrasil/views.py
gisbrasil/data/brasil/55mu2500gsd.dbf
gisbrasil/data/brasil/55mu2500gsd.prj
gisbrasil/data/brasil/55mu2500gsd.sbn
gisbrasil/data/brasil/55mu2500gsd.sbx
gisbrasil/data/brasil/55mu2500gsd.shp
gisbrasil/data/brasil/55mu2500gsd.shp.xml
gisbrasil/data/brasil/55mu2500gsd.shx
gisbrasil/data/brasil/readme.txt
gisbrasil/data/rs/portoalegre/bairros_utm22_sad69.dbf
gisbrasil/data/rs/portoalegre/bairros_utm22_sad69.prj
gisbrasil/data/rs/portoalegre/bairros_utm22_sad69.sbn
gisbrasil/data/rs/portoalegre/bairros_utm22_sad69.sbx
gisbrasil/data/rs/portoalegre/bairros_utm22_sad69.shp
gisbrasil/data/rs/portoalegre/bairros_utm22_sad69.shp.xml
gisbrasil/data/rs/portoalegre/bairros_utm22_sad69.shx
gisbrasil/data/rs/portoalegre/eixos_ruas_utm22_sad69.dbf
gisbrasil/data/rs/portoalegre/eixos_ruas_utm22_sad69.prj
gisbrasil/data/rs/portoalegre/eixos_ruas_utm22_sad69.sbn
gisbrasil/data/rs/portoalegre/eixos_ruas_utm22_sad69.sbx
gisbrasil/data/rs/portoalegre/eixos_ruas_utm22_sad69.shp
gisbrasil/data/rs/portoalegre/eixos_ruas_utm22_sad69.shp.xml
gisbrasil/data/rs/portoalegre/eixos_ruas_utm22_sad69.shx
gisbrasil/data/rs/portoalegre/readme.txt
gisbrasil/dataimport/__init__.py
gisbrasil/dataimport/base.py
gisbrasil/dataimport/brasil.py
gisbrasil/dataimport/rs/__init__.py
gisbrasil/dataimport/rs/portoalegre.py
gisbrasil/management/__init__.py
gisbrasil/management/commands/__init__.py
gisbrasil/management/commands/gisloader.py