Metadata-Version: 1.1
Name: django-gis-brasil
Version: 0.3
Summary: Django GIS Brasil is a Django app (GeoDjango) with Brazilian GIS information.
Home-page: https://github.com/perone/django-gis-brasil
Author: CodeFi.sh Team (Christian S. Perone, Leandro Nunes, Gabriel Wainer)
Author-email: christian.perone@gmail.com
License: BSD License
Platform: UNKNOWN
Classifier: Environment :: Web Environment
Classifier: Framework :: Django
Classifier: Intended Audience :: Developers
Classifier: License :: OSI Approved :: BSD License
Classifier: Operating System :: OS Independent
Classifier: Programming Language :: Python
Classifier: Programming Language :: Python :: 2.6
Classifier: Programming Language :: Python :: 2.7
Classifier: Topic :: Internet :: WWW/HTTP
Classifier: Topic :: Internet :: WWW/HTTP :: Dynamic Content
